dscal/__init__.py
dscal/dsmath/__init__.py
dscal/gui/__init__.py
dscal/tools/__init__.py
dscal-3.2.5.dist-info/LICENSE.TXT
dscal-3.2.5.dist-info/METADATA
dscal-3.2.5.dist-info/WHEEL
dscal-3.2.5.dist-info/top_level.txt
dscal-3.2.5.dist-info/RECORD
