Metadata-Version: 2.1
Name: dscal
Version: 3.2.5
Summary: Quick solutions to calculus and mathematical operations.
Home-page: https://sites.google.com/view/dscal3/home
Author: Dhruv Sehwal
Author-email: zarexdhruv@gmail.com
License: MIT
Platform: UNKNOWN
Requires-Dist: matplotlib
Requires-Dist: numexpr
Requires-Dist: sympy
